ducklakexl/__init__.py
ducklakexl/ducklake_test_2025-06-12_13-45-26.ducklake
ducklakexl/ducklake_test_2025-06-12_13-45-33.ducklake
ducklakexl/ducklake_test_2025-06-12_22-21-25.ducklake
ducklakexl/ducklake_test_2025-06-12_22-22-31.ducklake
ducklakexl/ducklake_test_2025-06-12_22-22-36.ducklake
ducklakexl/ducklake_test_2025-06-12_23-03-51.ducklake
ducklakexl/ducklake_test_2025-06-12_23-03-55.ducklake
ducklakexl/ducklake_test_2025-06-12_23-04-29.ducklake
ducklakexl/ducklake_test_2025-06-12_23-09-31.ducklake
ducklakexl/ducklake_test_2025-06-12_23-09-35.ducklake
ducklakexl/ducklake_test_2025-06-12_23-10-06.ducklake
ducklakexl/ducklakexl.py
ducklakexl-0.1.4.dist-info/licenses/LICENSE
ducklakexl-0.1.4.dist-info/WHEEL
ducklakexl-0.1.4.dist-info/METADATA
ducklakexl-0.1.4.dist-info/RECORD
