Metadata-Version: 2.4
Name: ducklakexl
Version: 0.1.4
Summary: Use Excel as a metadata catalog for DuckLake
Author: Greg Wilson
License-Expression: MIT
License-File: LICENSE
Requires-Dist: aiohttp>=3.12.11
Requires-Dist: azure-identity>=1.23.0
Requires-Dist: duckdb>=1.3.0
Requires-Dist: msal>=1.32.3
Requires-Dist: nest-asyncio>=1.6.0
Requires-Dist: openpyxl>=3.1.5
Requires-Dist: pandas>=2.2.3
Requires-Dist: python-dotenv>=1.1.0
Requires-Dist: requests>=2.32.3
Requires-Python: >=3.12
Project-URL: GitHub, https://github.com/gregwdata/ducklakexl
